README.rst
setup.cfg
setup.py
timeutils/__init__.py
timeutils/_version.py
timeutils/stopwatch.py
timeutils/timespan.py
timeutils.egg-info/PKG-INFO
timeutils.egg-info/SOURCES.txt
timeutils.egg-info/dependency_links.txt
timeutils.egg-info/top_level.txt
timeutils/tests/__init__.py
timeutils/tests/common_tests.py
timeutils/tests/stopwatch_test.py
timeutils/tests/timespan_test.py