Metadata-Version: 1.1
Name: timeutils
Version: 0.3.0
Summary: A set of methods and classes to accurately measure elapsed time.
Home-page: https://gitlab.com/cmick/timeutils
Author: Michal Ciesielczyk
Author-email: michal.ciesielczyk@put.poznan.pl
License: MIT
Download-URL: https://gitlab.com/cmick/timeutils/repository/v0.3.0/archive.tar.gz
Platform: UNKNOWN
Classifier: Development Status :: 3 - Alpha
Classifier: Topic :: Scientific/Engineering
Classifier: Topic :: Software Development
Classifier: Intended Audience :: Developers
Classifier: Intended Audience :: Science/Research
Classifier: License :: OSI Approved :: MIT License
Classifier: Operating System :: OS Independent
Classifier: Programming Language :: Python :: 2.7
Classifier: Programming Language :: Python :: 3.3
Classifier: Programming Language :: Python :: 3.4
Classifier: Programming Language :: Python :: 3.5
Classifier: Programming Language :: Python :: 3.6
